{
  "trainingType": "veg_SAC__carn_PPO",
  "trainingContent": {
    "brainTypeVegan": "SAC",
    "veganContent": {
      "survivorPercentageVegan": [
        0.0,
        0.0,
        0.0,
        0.0,
        0.0,
        0.0,
        0.0,
        0.0,
        0.0,
        0.0,
        0.0,
        0.0,
        0.0,
        0.0,
        0.0,
        0.0,
        0.0,
        0.0,
        0.0,
        0.0,
        0.0,
        0.0,
        0.0,
        0.0,
        0.0333333351,
        0.0,
        0.0,
        0.0,
        0.0,
        0.0,
        0.0,
        0.0,
        0.0,
        0.0,
        0.0,
        0.0333333351,
        0.0333333351,
        0.0,
        0.0,
        0.0,
        0.0333333351,
        0.0,
        0.0,
        0.0,
        0.0333333351,
        0.0,
        0.0,
        0.0333333351,
        0.0,
        0.0,
        0.03448276,
        0.0,
        0.0,
        0.0,
        0.0,
        0.0,
        0.0333333351,
        0.0,
        0.0,
        0.0,
        0.0333333351,
        0.0,
        0.0,
        0.0,
        0.0,
        0.0,
        0.0,
        0.0,
        0.0,
        0.0,
        0.0,
        0.0,
        0.0,
        0.0,
        0.0,
        0.0,
        0.0,
        0.0,
        0.0,
        0.0,
        0.0,
        0.0,
        0.0,
        0.0,
        0.0,
        0.0,
        0.03448276,
        0.0,
        0.0333333351,
        0.0,
        0.0,
        0.0,
        0.0,
        0.0333333351,
        0.0,
        0.0,
        0.0,
        0.0,
        0.0,
        0.0
      ],
      "survivorAvgAgeVegan": [
        2279.6,
        2558.1,
        2027.10339,
        1810.16663,
        2195.53345,
        2008.4,
        1900.03442,
        2165.33325,
        1826.8,
        1889.6333,
        2015.862,
        2113.7,
        2188.2334,
        1817.6,
        2322.34473,
        2153.7334,
        1848.53333,
        1994.53333,
        1819.931,
        2174.16675,
        1818.33337,
        2089.3667,
        2045.20691,
        1965.93335,
        2284.56665,
        2577.66675,
        1591.37927,
        2632.2334,
        2179.46655,
        2054.56665,
        2217.48267,
        2138.7666,
        1772.23328,
        2290.1333,
        2112.10352,
        2235.6,
        2054.7334,
        2141.53345,
        1698.37927,
        2499.1,
        2366.2334,
        1520.0,
        1785.24133,
        1891.1333,
        2106.46655,
        1748.6333,
        2674.3103,
        2059.0,
        2123.66675,
        2445.7,
        1947.03442,
        1918.53333,
        1769.53333,
        1526.76672,
        2241.0,
        1857.83337,
        2281.66675,
        1747.1,
        1973.6897,
        1835.1,
        1865.8667,
        1862.43335,
        1827.17236,
        2268.3,
        1770.3667,
        2052.6333,
        2233.10352,
        2147.7334,
        1733.8,
        1557.43335,
        2714.724,
        2206.7334,
        2057.7666,
        1830.03333,
        1733.10339,
        1913.93335,
        1938.1,
        2229.4,
        2310.55176,
        2061.16675,
        2116.46655,
        2074.0,
        2116.79321,
        1896.73328,
        2219.03345,
        1479.53333,
        1931.82764,
        2218.96655,
        2537.06665,
        2811.43335,
        1971.55176,
        1941.83337,
        1568.23328,
        1866.6,
        2511.41382,
        2383.1,
        1698.73328,
        2188.2,
        2170.03442,
        1913.8
      ]
    },
    "brainTypeCarnivore": "PPO",
    "carnivoreContent": {
      "survivorPercentageCarnivore": [
        0.8666667,
        0.4,
        0.8666667,
        0.733333349,
        0.733333349,
        0.8,
        0.6,
        0.8,
        0.8,
        0.8,
        0.933333337,
        0.8,
        0.6666667,
        0.8666667,
        0.733333349,
        1.0,
        1.0,
        0.933333337,
        0.6,
        0.6666667,
        1.0,
        0.6,
        0.8666667,
        0.8666667,
        0.333333343,
        0.8,
        0.8666667,
        0.733333349,
        0.6,
        0.8666667,
        0.733333349,
        0.8,
        0.733333349,
        0.8,
        0.933333337,
        0.733333349,
        0.533333361,
        0.733333349,
        0.8666667,
        0.6,
        0.8666667,
        0.733333349,
        0.4,
        0.8666667,
        0.733333349,
        0.8,
        0.6,
        0.6666667,
        0.8,
        0.4,
        0.8,
        0.8,
        0.733333349,
        0.333333343,
        0.733333349,
        0.8666667,
        0.8,
        0.8666667,
        0.8,
        0.933333337,
        0.933333337,
        0.6,
        0.8,
        0.8,
        0.6,
        0.6,
        0.733333349,
        0.8,
        0.6666667,
        0.733333349,
        0.6666667,
        0.8666667,
        0.733333349,
        0.8,
        0.6666667,
        0.6666667,
        0.8,
        0.8,
        0.466666669,
        0.933333337,
        0.6,
        0.6666667,
        0.6,
        0.933333337,
        0.6666667,
        0.6666667,
        0.8,
        0.6666667,
        0.733333349,
        0.333333343,
        1.0,
        0.933333337,
        0.6,
        0.466666669,
        0.8666667,
        0.8,
        0.8666667,
        0.733333349,
        0.8,
        0.8666667
      ],
      "survivorAvgAgeCarnivore": [
        9316.2,
        7378.467,
        9784.066,
        9469.866,
        8534.467,
        8947.066,
        7704.2,
        9453.066,
        9396.333,
        8963.467,
        9622.667,
        9122.733,
        9034.667,
        9476.2,
        8449.267,
        10000.0,
        10000.0,
        9703.6,
        8786.6,
        9014.533,
        10000.0,
        8601.667,
        9412.0,
        9230.467,
        8032.4,
        9168.134,
        9548.134,
        8525.533,
        8404.066,
        9176.2,
        9297.866,
        9013.866,
        8966.0,
        9258.2,
        9932.333,
        8989.2,
        8410.6,
        8758.4,
        9136.134,
        7664.467,
        9478.467,
        9141.667,
        8209.134,
        9396.8,
        8324.733,
        9512.333,
        8063.3335,
        8802.2,
        8760.667,
        7591.8,
        9003.667,
        9105.667,
        9153.8,
        6727.6,
        9187.6,
        9477.533,
        9290.066,
        9435.6,
        8766.467,
        9783.8,
        9750.667,
        8863.866,
        9493.0,
        9148.333,
        8657.866,
        8597.134,
        8650.4,
        9253.066,
        8681.333,
        8873.733,
        8342.667,
        9119.6,
        8654.467,
        8909.934,
        9173.333,
        8687.6,
        9557.467,
        9246.267,
        7570.8667,
        9550.4,
        7563.6665,
        8412.733,
        8426.467,
        9563.6,
        8664.667,
        8492.866,
        9311.8,
        9193.533,
        8707.467,
        6496.7334,
        10000.0,
        9678.267,
        9371.4,
        7619.1333,
        9404.066,
        9438.333,
        9493.134,
        9237.0,
        8701.733,
        9431.733
      ]
    }
  }
}